torrent_organizer/__init__.py
torrent_organizer/config.py
torrent_organizer/console/__init__.py
torrent_organizer/console/run.py
torrent_organizer/exceptions.py
torrent_organizer/models.py
torrent_organizer/organize.py
torrent_organizer/utils.py
torrent_organizer-0.1.2.dist-info/entry_points.txt
torrent_organizer-0.1.2.dist-info/WHEEL
torrent_organizer-0.1.2.dist-info/METADATA
torrent_organizer-0.1.2.dist-info/RECORD
